fulladder/fulladder.vhdl
entity fa is
  -- i0, i1 and the carry-in ci are inputs of the adder.
  -- s is the sum output, and co is the carry-out.
  port (i0, i1: in bit; ci: in bit; s: out bit; co: out bit);
end fa;

architecture rtl of fa is
begin
-- This full-adder architecture contains two concurrent assignment.
-- Compute the sum.
  s <= i0 xor i1 xor ci;
  -- Compute the carry.
  co <= (i0 and i1) or (i0 and ci) or (i1 and ci);
end rtl;

fulladder/fulladder_tb.vhdl
-- A testbench has no ports.
entity fa_tb is
end fa_tb;

architecture behav of fa_tb is
-- Declaration of the component that will be instantiated.
component fa
  port (i0, i1: in bit; ci: in bit; s: out bit; co: out bit);
end component;

-- Specify which entity is bound with the component.
for fa_0: fa use entity work.fa;

signal i0, i1, ci, s, co: bit;

begin

-- Component instantiation.
  fa_0: fa port map (
    i0 => i0,
    i1 => i1,
    ci => ci,
    s => s,
    co => co
  );

-- This process does the real job.
  process
    type pattern_type is record
    -- The inputs of the adder.
    i0, i1, ci: bit;
    -- The expected outputs of the adder.
    s, co: bit;
  end record;

  -- The patterns to apply.
  type pattern_array is array (natural range <>) of pattern_type;
  constant patterns: pattern_array := (
  ('0', '0', '0', '0', '0'),
  ('0', '0', '1', '1', '0'),
  ('0', '1', '0', '1', '0'),
  ('0', '1', '1', '0', '1'),
  ('1', '0', '0', '1', '0'),
  ('1', '0', '1', '0', '1'),
  ('1', '1', '0', '0', '1'),
  ('1', '1', '1', '1', '1')
  );

  begin
    -- Check each pattern.
    for i in patterns'range loop
      -- Set the inputs.
      i0 <= patterns(i).i0;
      i1 <= patterns(i).i1;
      ci <= patterns(i).ci;
      -- Wait for the results.
      wait for 1 ns;
      -- Check the outputs.
      assert s = patterns(i).s
        report "bad sum value" severity error;
      assert co = patterns(i).co
        report "bad carry out value" severity error;
      end loop;

      assert false report "end of test" severity note;
      -- Wait forever; this will finish the simulation.
      wait;
    end process;
end behav;

fulladder/fa.vcd
$date
  Sat Jun 22 17:36:06 2024
$end
$version
  GHDL v0
$end
$timescale
  1 fs
$end
$scope module standard $end
$upscope $end
$scope module fa_tb $end
$var reg 1 ! i0 $end
$var reg 1 " i1 $end
$var reg 1 # ci $end
$var reg 1 $ s $end
$var reg 1 % co $end
$scope module fa_0 $end
$var reg 1 & i0 $end
$var reg 1 ' i1 $end
$var reg 1 ( ci $end
$var reg 1 ) s $end
$var reg 1 * co $end
$upscope $end
$upscope $end
$enddefinitions $end
#0
0!
0"
0#
0$
0%
0&
0'
0(
0)
0*
#1000000
1#
1$
1(
1)
#2000000
1"
0#
1'
0(
#3000000
1#
0$
1%
1(
0)
1*
#4000000
1!
0"
0#
1$
0%
1&
0'
0(
1)
0*
#5000000
1#
0$
1%
1(
0)
1*
#6000000
1"
0#
1'
0(
#7000000
1#
1$
1(
1)
