mips/32Mux2to1.vhd
-- 32Mux2to1.vhd
-- Implementation of 32-bit MUX 2:1

library ieee;
use ieee.std_logic_1164.all;

entity mux2_32 is
port (
  i0, i1: in std_logic_vector(31 downto 0);
  o: out std_logic_vector(31 downto 0);
  sel: in std_logic
);
end entity mux2_32;

architecture behavioral of mux2_32 is
begin
  o <= i0 when sel = '0' else i1;
end architecture behavioral;

mips/32Mux2to1_tb.vhd
-- 32Mux2to1_tb.vhd
-- Test Bench for 32-bit 2:1 MUX

library ieee;
use ieee.std_logic_1164.all;

entity mux2_32_tb is end entity mux2_32_tb;

architecture behavioral of mux2_32_tb is
  component mux2_32
  port (
    i0, i1: in std_logic_vector(31 downto 0); 
    o: out std_logic_vector(31 downto 0);
    sel: in std_logic
  );
  end component;

  signal i0, i1, o: std_logic_vector(31 downto 0);
  signal sel: std_logic;

begin
  uut: mux2_32 port map (
    i0 => i0,
    i1 => i1,
    o => o,
    sel => sel
  );

  stim_proc: process
    type pattern_type is record
      i0, i1: std_logic_vector(31 downto 0);
      sel: std_logic;
      o: std_logic_vector(31 downto 0);
    end record;

    type pattern_array is array (natural range <>) of pattern_type;
    constant patterns: pattern_array := (
      -- sel = '0', output should be i0
      (x"00000000", x"FFFFFFFF", '0', x"00000000"),
      (x"AAAAAAAA", x"55555555", '0', x"AAAAAAAA"),
      (x"12345678", x"87654321", '0', x"12345678"),
      (x"FFFFFFFF", x"00000000", '0', x"FFFFFFFF"),
      (x"0F0F0F0F", x"F0F0F0F0", '0', x"0F0F0F0F"),
      -- sel = '1', output should be i1
      (x"00000000", x"FFFFFFFF", '1', x"FFFFFFFF"),
      (x"AAAAAAAA", x"55555555", '1', x"55555555"),
      (x"12345678", x"87654321", '1', x"87654321"),
      (x"FFFFFFFF", x"00000000", '1', x"00000000"),
      (x"0F0F0F0F", x"F0F0F0F0", '1', x"F0F0F0F0"),

      -- Required test cases
      (x"AAAAAAAA", x"BBBBBBBB", '1', x"BBBBBBBB"), -- sel = '1', output should be i1
      (x"AAAAAAAA", x"BBBBBBBB", '0', x"AAAAAAAA")  -- sel = '0', output should be i0
    );

  begin
    for i in patterns'range loop

      i0 <= patterns(i).i0;
      i1 <= patterns(i).i1;
      sel <= patterns(i).sel;

      wait for 10 ns;

      assert o = patterns(i).o
      report "test failed for pattern " & integer'image(i)
      severity error;

    end loop;

    report "end of simulation"
    severity note;
    wait;

  end process;

end architecture behavioral;

mips/32Mux2to1.vcd
$date
  Mon Jun 24 01:41:39 2024
$end
$version
  GHDL v0
$end
$timescale
  1 fs
$end
$scope module standard $end
$upscope $end
$scope module std_logic_1164 $end
$upscope $end
$scope module mux2_32_tb $end
$var reg 32 ! i0[31:0] $end
$var reg 32 " i1[31:0] $end
$var reg 32 # o[31:0] $end
$var reg 1 $ sel $end
$scope module uut $end
$var reg 32 % i0[31:0] $end
$var reg 32 & i1[31:0] $end
$var reg 32 ' o[31:0] $end
$var reg 1 ( sel $end
$upscope $end
$upscope $end
$enddefinitions $end
#0
b00000000000000000000000000000000 !
b11111111111111111111111111111111 "
b00000000000000000000000000000000 #
0$
b00000000000000000000000000000000 %
b11111111111111111111111111111111 &
b00000000000000000000000000000000 '
0(
#10000000
b10101010101010101010101010101010 !
b01010101010101010101010101010101 "
b10101010101010101010101010101010 #
b10101010101010101010101010101010 %
b01010101010101010101010101010101 &
b10101010101010101010101010101010 '
#20000000
b00010010001101000101011001111000 !
b10000111011001010100001100100001 "
b00010010001101000101011001111000 #
b00010010001101000101011001111000 %
b10000111011001010100001100100001 &
b00010010001101000101011001111000 '
#30000000
b11111111111111111111111111111111 !
b00000000000000000000000000000000 "
b11111111111111111111111111111111 #
b11111111111111111111111111111111 %
b00000000000000000000000000000000 &
b11111111111111111111111111111111 '
#40000000
b00001111000011110000111100001111 !
b11110000111100001111000011110000 "
b00001111000011110000111100001111 #
b00001111000011110000111100001111 %
b11110000111100001111000011110000 &
b00001111000011110000111100001111 '
#50000000
b00000000000000000000000000000000 !
b11111111111111111111111111111111 "
b11111111111111111111111111111111 #
1$
b00000000000000000000000000000000 %
b11111111111111111111111111111111 &
b11111111111111111111111111111111 '
1(
#60000000
b10101010101010101010101010101010 !
b01010101010101010101010101010101 "
b01010101010101010101010101010101 #
b10101010101010101010101010101010 %
b01010101010101010101010101010101 &
b01010101010101010101010101010101 '
#70000000
b00010010001101000101011001111000 !
b10000111011001010100001100100001 "
b10000111011001010100001100100001 #
b00010010001101000101011001111000 %
b10000111011001010100001100100001 &
b10000111011001010100001100100001 '
#80000000
b11111111111111111111111111111111 !
b00000000000000000000000000000000 "
b00000000000000000000000000000000 #
b11111111111111111111111111111111 %
b00000000000000000000000000000000 &
b00000000000000000000000000000000 '
#90000000
b00001111000011110000111100001111 !
b11110000111100001111000011110000 "
b11110000111100001111000011110000 #
b00001111000011110000111100001111 %
b11110000111100001111000011110000 &
b11110000111100001111000011110000 '
#100000000
b10101010101010101010101010101010 !
b10111011101110111011101110111011 "
b10111011101110111011101110111011 #
b10101010101010101010101010101010 %
b10111011101110111011101110111011 &
b10111011101110111011101110111011 '
#110000000
b10101010101010101010101010101010 #
0$
b10101010101010101010101010101010 '
0(
