mips/Imem.vhd
-- Imem.vhd
-- Implementation of Instruction Memory (ROM)
library ieee;
use ieee.std_logic_1164.all;
use ieee.numeric_std.all;

entity imem is
port (
  addr: in std_logic_vector(31 downto 0);
  instruction: out std_logic_vector(31 downto 0)
);
end entity imem;

architecture behavioral of imem is
  type mem_type is array (0 to 15) of std_logic_vector(31 downto 0);
  signal mem : mem_type := (
    0 => x"20000000", -- addi $0, $0, 0
    1 => x"20420000", -- addi $2, $2, 0
    2 => x"20820000", -- addi $2, $4, 0
    3 => x"20030001", -- addi $3, $0, 1
    4 => x"20050003", -- addi $5, $0, 3
    5 => x"00603020", -- add $6, $3, $0
    6 => x"ac860000", -- sw $6, 0($4)
    7 => x"20630001", -- addi $3, $3, 1
    8 => x"20840001", -- addi $4, $4, 1
    9 => x"20a5ffff", -- addi $5, $5, -1
   10 => x"14a0fffa", -- bne $5, $0, L1
   others => (others => '0')
  );
begin

  main: process (addr)
    variable a: integer;
  begin
    a := to_integer(unsigned(addr));
    if a < 0 or a > 15 then
      instruction <= (others => 'X');
    else
      instruction <= mem(a);
    end if;
  end process;

end architecture behavioral;

mips/Imem_tb.vhd
-- Imem_tb.vhd
-- Test Bench for Instruction Memory (ROM)
library ieee;
use ieee.std_logic_1164.all;
use ieee.numeric_std.all;

entity imem_tb is end entity imem_tb;

architecture behavioral of imem_tb is

  component imem is
  port (
    addr: in std_logic_vector(31 downto 0);
    instruction: out std_logic_vector(31 downto 0)
  );
  end component imem;

  constant CLK_PERIOD : time := 10 ns;

  signal addr : std_logic_vector(31 downto 0) := (others => '0');
  signal instruction_out : std_logic_vector(31 downto 0) := (others => '0');

  type mem_type is array (0 to 15) of std_logic_vector(31 downto 0);
  signal mem : mem_type := (
    0 => x"20000000", -- addi $0, $0, 0
    1 => x"20420000", -- addi $2, $2, 0
    2 => x"20820000", -- addi $2, $4, 0
    3 => x"20030001", -- addi $3, $0, 1
    4 => x"20050003", -- addi $5, $0, 3
    5 => x"00603020", -- add $6, $3, $0
    6 => x"ac860000", -- sw $6, 0($4)
    7 => x"20630001", -- addi $3, $3, 1
    8 => x"20840001", -- addi $4, $4, 1
    9 => x"20a5ffff", -- addi $5, $5, -1
   10 => x"14a0fffa", -- bne $5, $0, L1
   others => (others => '0')
  );

begin

  uut: imem port map (
    addr => addr,
    instruction => instruction_out
  );

  stim_proc : process
  begin
    for i in mem'range loop
      addr <= std_logic_vector(to_unsigned(i, 32));
      wait for CLK_PERIOD;
      assert instruction_out = mem(i)
        report "instruction mismatch at address " & integer'image(i)
        severity error;
    end loop;

    report "end of simulation"
    severity note;
    wait;

  end process stim_proc;

end architecture behavioral;

mips/Imem.vcd
$date
  Fri Jun 28 00:11:13 2024
$end
$version
  GHDL v0
$end
$timescale
  1 fs
$end
$scope module standard $end
$upscope $end
$scope module std_logic_1164 $end
$upscope $end
$scope module numeric_std $end
$upscope $end
$scope module imem_tb $end
$var reg 32 ! addr[31:0] $end
$var reg 32 " instruction_out[31:0] $end
$comment mem is not handled $end
$scope module uut $end
$var reg 32 # addr[31:0] $end
$var reg 32 $ instruction[31:0] $end
$comment mem is not handled $end
$upscope $end
$upscope $end
$enddefinitions $end
#0
b00000000000000000000000000000000 !
b00100000000000000000000000000000 "
b00000000000000000000000000000000 #
b00100000000000000000000000000000 $
#10000000
b00000000000000000000000000000001 !
b00100000010000100000000000000000 "
b00000000000000000000000000000001 #
b00100000010000100000000000000000 $
#20000000
b00000000000000000000000000000010 !
b00100000100000100000000000000000 "
b00000000000000000000000000000010 #
b00100000100000100000000000000000 $
#30000000
b00000000000000000000000000000011 !
b00100000000000110000000000000001 "
b00000000000000000000000000000011 #
b00100000000000110000000000000001 $
#40000000
b00000000000000000000000000000100 !
b00100000000001010000000000000011 "
b00000000000000000000000000000100 #
b00100000000001010000000000000011 $
#50000000
b00000000000000000000000000000101 !
b00000000011000000011000000100000 "
b00000000000000000000000000000101 #
b00000000011000000011000000100000 $
#60000000
b00000000000000000000000000000110 !
b10101100100001100000000000000000 "
b00000000000000000000000000000110 #
b10101100100001100000000000000000 $
#70000000
b00000000000000000000000000000111 !
b00100000011000110000000000000001 "
b00000000000000000000000000000111 #
b00100000011000110000000000000001 $
#80000000
b00000000000000000000000000001000 !
b00100000100001000000000000000001 "
b00000000000000000000000000001000 #
b00100000100001000000000000000001 $
#90000000
b00000000000000000000000000001001 !
b00100000101001011111111111111111 "
b00000000000000000000000000001001 #
b00100000101001011111111111111111 $
#100000000
b00000000000000000000000000001010 !
b00010100101000001111111111111010 "
b00000000000000000000000000001010 #
b00010100101000001111111111111010 $
#110000000
b00000000000000000000000000001011 !
b00000000000000000000000000000000 "
b00000000000000000000000000001011 #
b00000000000000000000000000000000 $
#120000000
b00000000000000000000000000001100 !
b00000000000000000000000000001100 #
#130000000
b00000000000000000000000000001101 !
b00000000000000000000000000001101 #
#140000000
b00000000000000000000000000001110 !
b00000000000000000000000000001110 #
#150000000
b00000000000000000000000000001111 !
b00000000000000000000000000001111 #
