mips/PC.vhd
-- PC.vhd
-- Implementation of Program Counter

library ieee;
use ieee.std_logic_1164.all;
use ieee.numeric_std.all;

entity pc is
port (
  input: in std_logic_vector(31 downto 0);
  clk, rst: in std_logic;
  output: out std_logic_vector(31 downto 0)
);
end entity pc;

architecture behavioral of pc is
  signal pc_internal: signed(31 downto 0);

begin

    process (clk, rst)
    begin
      if rst = '1' then
        pc_internal <= to_signed(0, pc_internal'length);
      elsif rising_edge(clk) then
        pc_internal <= signed(input);
      end if;
    end process;

    output <= std_logic_vector(pc_internal);

end architecture behavioral;

mips/PC_tb.vhd
-- PC_tb.vhd
-- Test bench of Program Counter (PC)

library ieee;
use ieee.std_logic_1164.all;
use ieee.numeric_std.all;

entity pc_tb is
end entity pc_tb;

architecture behavioral of pc_tb is
  component pc
    port (
      input: in std_logic_vector(31 downto 0);
      clk, rst: in std_logic;
      output: out std_logic_vector(31 downto 0)
    );
  end component pc;

  signal clk: std_logic := '0';
  signal rst: std_logic := '0';
  signal input: std_logic_vector(31 downto 0) := (others => '0');
  signal output: std_logic_vector(31 downto 0);

  constant CLOCK_PERIOD: time := 10 ns;

begin

  uut: pc port map (
    input => input,
    clk => clk,
    rst => rst,
    output => output
  );

  clk_proc: process
  begin
    while now < 200 ns loop
      clk <= '0';
      wait for CLOCK_PERIOD / 2;
      clk <= '1';
      wait for CLOCK_PERIOD / 2;
    end loop;
    wait;
  end process clk_proc;

  stim_proc: process

      type pattern_type is record
        input: std_logic_vector(31 downto 0);
        output: std_logic_vector(31 downto 0);
      end record;

      type pattern_array is array (natural range <>) of pattern_type;

      constant patterns: pattern_array := (
      (x"00000010", x"00000010"),  -- Load PC with 0x00000010
      (x"00000100", x"00000100"),  -- Load PC with 0x00000100
      (x"FFFFFFF0", x"FFFFFFF0"),  -- Load PC with 0xFFFFFFF0

      -- Required test cases
      (x"AAAA_BBBB", x"AAAA_BBBB"),
      (x"FFFF_CCCC", x"FFFF_CCCC")
      );
  begin
    rst <= '1';
    wait for CLOCK_PERIOD;
    rst <= '0';
    wait for CLOCK_PERIOD;

    for i in patterns'range loop
      input <= patterns(i).input;
      wait for CLOCK_PERIOD;

      assert output = patterns(i).output
      report "test failed for pattern " & integer'image(i)
      severity error;

      wait for CLOCK_PERIOD;
    end loop;

    report "end of simulation"
    severity note;
    wait;

  end process stim_proc;

end architecture behavioral;

mips/PC.vcd
$date
  Sat Jun 29 00:20:47 2024
$end
$version
  GHDL v0
$end
$timescale
  1 fs
$end
$scope module standard $end
$upscope $end
$scope module std_logic_1164 $end
$upscope $end
$scope module numeric_std $end
$upscope $end
$scope module pc_tb $end
$var reg 1 ! clk $end
$var reg 1 " rst $end
$var reg 32 # input[31:0] $end
$var reg 32 $ output[31:0] $end
$scope module uut $end
$var reg 32 % input[31:0] $end
$var reg 1 & clk $end
$var reg 1 ' rst $end
$var reg 32 ( output[31:0] $end
$var reg 32 ) pc_internal[31:0] $end
$upscope $end
$upscope $end
$enddefinitions $end
#0
0!
1"
b00000000000000000000000000000000 #
b00000000000000000000000000000000 $
b00000000000000000000000000000000 %
0&
1'
b00000000000000000000000000000000 (
b00000000000000000000000000000000 )
#5000000
1!
1&
#10000000
0!
0"
0&
0'
#15000000
1!
1&
#20000000
0!
b00000000000000000000000000010000 #
b00000000000000000000000000010000 %
0&
#25000000
1!
b00000000000000000000000000010000 $
1&
b00000000000000000000000000010000 (
b00000000000000000000000000010000 )
#30000000
0!
0&
#35000000
1!
1&
#40000000
0!
b00000000000000000000000100000000 #
b00000000000000000000000100000000 %
0&
#45000000
1!
b00000000000000000000000100000000 $
1&
b00000000000000000000000100000000 (
b00000000000000000000000100000000 )
#50000000
0!
0&
#55000000
1!
1&
#60000000
0!
b11111111111111111111111111110000 #
b11111111111111111111111111110000 %
0&
#65000000
1!
b11111111111111111111111111110000 $
1&
b11111111111111111111111111110000 (
b11111111111111111111111111110000 )
#70000000
0!
0&
#75000000
1!
1&
#80000000
0!
b10101010101010101011101110111011 #
b10101010101010101011101110111011 %
0&
#85000000
1!
b10101010101010101011101110111011 $
1&
b10101010101010101011101110111011 (
b10101010101010101011101110111011 )
#90000000
0!
0&
#95000000
1!
1&
#100000000
0!
b11111111111111111100110011001100 #
b11111111111111111100110011001100 %
0&
#105000000
1!
b11111111111111111100110011001100 $
1&
b11111111111111111100110011001100 (
b11111111111111111100110011001100 )
